SpatialPerturb/__init__.py
SpatialPerturb/cli.py
SpatialPerturb/signatures.py
spatialperturb-0.1.0.dist-info/licenses/LICENSE
spatialperturb-0.1.0.dist-info/METADATA
spatialperturb-0.1.0.dist-info/WHEEL
spatialperturb-0.1.0.dist-info/entry_points.txt
spatialperturb-0.1.0.dist-info/top_level.txt
spatialperturb-0.1.0.dist-info/RECORD
